{
    "with_exploration": true,
    "with_reconstruction": true,
    //Reconstruction Flags
    "with_continuous_height_flag": false,
    "with_erosion_flag": false,
    "double_flag": false,
    "split_flag": false,
    "cluster_duplicate_flag": false,
    //Exploration Flags
    "fix_angle_flag": true,
    "explore_multi_angle": false,

    // Reconstruction parameters
    "view_distance": 40,
    "safe_distance": 25,
    "vertical_overlap": 0.4,
    "horizontal_overlap": 0.1,
    "split_overlap": 0.5,
    "z_down_bounds": 40, //Optinal

    "fov": 53,

    "HEIGHT_CLIP": 10, // Effect the clustering of the buildings. Do not important here, we manually select a good point cloud for clustering
    "MERGED_THRESHOLD": -1,
    "SPLIT_THRESHOLD": 100,
    "heightmap_resolution": 5,
    "heightmap_dilate": 0,
    "cluster_radius": 10,
    "model_path1": "F:\\Sig\\Real\\paper_2nd\\2_3_global\\Shanghai_points_2.ply",
    "safe_zone_model_path1": "F:\\Sig\\Real\\paper_2nd\\2_3_global\\Shanghai_points_2.ply",
    "mesh_root1": "F:\\DataSet\\Shenzhen\\SZU_split_latest\\split",
    "color_map1": "F:\\Unreal\\City\\Plugins\\AirSim\\Content\\HUDAssets\\seg_color_pallet.png",

    "model_path": "F:\\Sig\\Real\\paper_2nd\\2_3_global\\Shanghai_points_2.ply",
    "safe_zone_model_path": "F:\\Sig\\Real\\paper_2nd\\2_3_global\\Shanghai_points_2.ply",
    "mesh_root": "D:\\DATASET\\Realcity\\ShenzhenUniv\\split\\split",
    "color_map": "D:\\env\\Env\\Plugins\\AirSim\\Content\\HUDAssets\\seg_color_pallet.png",

    "is_viz": true,
    "is_viz1": false,
    "is_log": true,

    //
    // These are all unreal coordinates
    // Y axis in invert, min y in unreal is max y in mesh
    //
    "START_X1": -27000.0,
    "START_Y1": 143000.0,
    "START_Z1": 4000.0,
    "MAP_START_UNREAL_X1": -10000.0,
    "MAP_START_UNREAL_Y1": -76000.0,
    "MAP_START_UNREAL_Z1": -500.0,
    "MAP_END_UNREAL_X1": 20000.0,
    "MAP_END_UNREAL_Y1": 43000.0,
    "MAP_END_UNREAL_Z1": 9000.0,

    "START_X": -27000.0,
    "START_Y": 143000.0,
    "START_Z": 4000.0,
    "MAP_START_UNREAL_X": -52000.0,
    "MAP_START_UNREAL_Y": -88000.0,
    "MAP_START_UNREAL_Z": -500.0,
    "MAP_END_UNREAL_X": 62000.0,
    "MAP_END_UNREAL_Y": 85000.0,
    "MAP_END_UNREAL_Z": 9000.0,


    "boundary": [
        113.93155427597746,
        22.529240818344984,
        0,
        113.93169429799778,
        22.532178550803582,
        0,
        113.92805906397743,
        22.532820952087242,
        0,
        113.92908687140991,
        22.540183851196872,
        0,
        113.93380399683271,
        22.541082871284154,
        0,
        113.9336967110383,
        22.535445757895992,
        0,
        113.93569568712458,
        22.532550822304977,
        0,
        113.9335641466518,
        22.529047857625905,
        0
    ],

    "DRONE_STEP": 10,
    "with_interpolated": false,

    "SYNTHETIC_POINT_CLOUD": true,
    "MAP_2D_BOX_TO_3D": true,
    "use_bbox_detect": false,
    //"mapper": "gt_mapper",
    //"mapper": "graduate_gt_mapper",
    "mapper": "Virtual_mapper",
    // "mapper": "real_mapper",

    "nbv_target1": "Topology_decomposition",
    "nbv_target3": "Min_distance",
    "nbv_target1": "Reconstruction_only",
    "nbv_target1": "Min_max_information",

    // Ablation study
    "nbv_target": "Exploration_first",
    "nbv_target1": "Random_min_distance",

    "CCPP_CELL_THRESHOLD": 5,
    "CCPP_Obstacle_weight": 2.5,
    "ccpp_cell_distance": 30,

    "output_waypoint": false,
    "geo_origin": [ 12682806.58230256, 2575925.37105384 ,0],
    "IOU_threshold": 0.7
}